<?xml version="1.0" encoding="UTF-8"?>

<!DOCTYPE configuration PUBLIC "-//mybatis.org//DTD Config 3.0//EN" "http://mybatis.org/dtd/mybatis-3-config.dtd">

<configuration>
    <typeAliases>
		<typeAlias alias="PersonVo" type="com.javaex.vo.UserVo" />
    </typeAliases>

    <mappers>
        <mapper resource="mybatis/mappers/user.xml" />
        <mapper resource="mybatis/mappers/guest.xml" />
        <mapper resource="mybatis/mappers/board.xml" />
        <mapper resource="mybatis/mappers/replyBoard.xml" />
        <mapper resource="mybatis/mappers/gallery.xml" />
    </mappers>
</configuration>
